AMN/__init__.py
AMN/__main__.py
AMN/am0.py
AMN/am1.py
AMN/main.py
AMN/py.typed
AMN/repl.py
amn-0.6.1.dist-info/METADATA
amn-0.6.1.dist-info/WHEEL
amn-0.6.1.dist-info/entry_points.txt
amn-0.6.1.dist-info/licenses/LICENSE
amn-0.6.1.dist-info/RECORD
