Metadata-Version: 2.1
Name: AMN
Version: 0.6.1
Summary: Virtual machines for the AMN instructions sets
Project-URL: Repository, https://github.com/Deric-W/AMN
Project-URL: Bugtracker, https://github.com/Deric-W/AMN/issues
Author-email: Eric Niklas Wolf <eric_niklas.wolf@mailbox.tu-dresden.de>
License-File: LICENSE
Keywords: AM0,AM1,AMN
Classifier: Environment :: Console
Classifier: Intended Audience :: Education
Classifier: License :: OSI Approved :: GNU General Public License v3 (GPLv3)
Classifier: Operating System :: OS Independent
Classifier: Programming Language :: Python :: 3 :: Only
Classifier: Topic :: Education
Classifier: Topic :: Utilities
Classifier: Typing :: Typed
Requires-Python: >=3.10
